build_phasing_graph-0.1.0.dist-info/METADATA
build_phasing_graph-0.1.0.dist-info/WHEEL
build_phasing_graph/__init__.py
build_phasing_graph/build_phasing_graph.abi3.so
build_phasing_graph-0.1.0.dist-info/RECORD
