Metadata-Version: 2.4
Name: build_phasing_graph
Version: 0.1.0
Requires-Python: >=3.8
